rich_pyfiglet/__init__.py
rich_pyfiglet/box_constants.py
rich_pyfiglet/cli.py
rich_pyfiglet/fonts_list.py
rich_pyfiglet/py.typed
rich_pyfiglet/rich_figlet.py
rich_pyfiglet-1.0.0.dist-info/WHEEL
rich_pyfiglet-1.0.0.dist-info/entry_points.txt
rich_pyfiglet-1.0.0.dist-info/METADATA
rich_pyfiglet-1.0.0.dist-info/RECORD
