Metadata-Version: 2.3
Name: rich-pyfiglet
Version: 1.0.0
Summary: A library that wraps PyFiglet with the Rich library for rendering ASCII art in the terminal.
Keywords: python,pyfiglet,figlet,ascii,rich,cli,color,terminal,banner
Author: edward-jazzhands
Author-email: edward-jazzhands <ed.jazzhands@gmail.com>
License: MIT
Classifier: Development Status :: 5 - Production/Stable
Classifier: License :: OSI Approved :: MIT License
Classifier: Operating System :: OS Independent
Classifier: Programming Language :: Python
Classifier: Programming Language :: Python :: 3.9
Classifier: Programming Language :: Python :: 3.10
Classifier: Programming Language :: Python :: 3.11
Classifier: Programming Language :: Python :: 3.12
Classifier: Programming Language :: Python :: 3.13
Classifier: Programming Language :: Python :: 3 :: Only
Requires-Dist: click>=8.1.8
Requires-Dist: pyfiglet>=1.0.3
Requires-Dist: rich>=12.0.0,<15.0.0
Requires-Python: >=3.9
Project-URL: Changelog, https://github.com/edward-jazzhands/rich-pyfiglet/blob/master/CHANGELOG.md
Project-URL: Repository, https://github.com/edward-jazzhands/rich-pyfiglet
